{
  "chief_complaints": [
    "Patient presents with a {duration}-day history of {symptom}.",
    "{age}-year-old {sex} with chief complaint of {symptom} for the past {duration} days.",
    "Reports new-onset {symptom} beginning approximately {duration} days ago.",
    "Follow-up visit for ongoing management of {chronic_condition}.",
    "Routine evaluation; patient reports intermittent {symptom}."
  ],
  "symptoms": [
    "chest pain",
    "shortness of breath",
    "low back pain",
    "abdominal pain",
    "headache",
    "dizziness",
    "fatigue",
    "cough",
    "fever",
    "nausea and vomiting",
    "joint pain",
    "swelling in lower extremities",
    "palpitations",
    "blurred vision"
  ],
  "chronic_conditions": [
    "Type 2 diabetes mellitus",
    "essential hypertension",
    "hyperlipidemia",
    "chronic obstructive pulmonary disease",
    "coronary artery disease",
    "congestive heart failure",
    "chronic kidney disease",
    "osteoarthritis",
    "depression",
    "hypothyroidism"
  ],
  "hpi_phrases": [
    "Pain is described as {quality}, rated {severity}/10, and is {pattern}.",
    "Symptoms are exacerbated by {trigger} and relieved by {reliever}.",
    "Denies associated {denied_symptom}.",
    "Patient reports compliance with current medication regimen.",
    "No prior episodes of similar symptoms.",
    "Symptoms have progressively worsened despite home management."
  ],
  "pain_quality": ["sharp", "dull", "aching", "burning", "throbbing", "pressure-like", "stabbing"],
  "pain_pattern": ["constant", "intermittent", "worse in the morning", "worse at night", "activity-related"],
  "triggers": ["physical exertion", "deep inspiration", "cold weather", "spicy foods", "prolonged standing", "stress"],
  "relievers": ["rest", "over-the-counter analgesics", "heat application", "ice", "antacids", "lying flat"],
  "denied_symptoms": ["radiation of pain", "diaphoresis", "syncope", "weight loss", "hemoptysis", "melena", "rash"],
  "ros_systems": [
    "Constitutional: Denies fever, chills, or weight changes.",
    "HEENT: No vision changes, sore throat, or congestion.",
    "Cardiovascular: Denies chest pain, palpitations, or edema.",
    "Respiratory: Denies cough, wheezing, or shortness of breath at rest.",
    "Gastrointestinal: Denies nausea, vomiting, diarrhea, or constipation.",
    "Genitourinary: Denies dysuria, frequency, or hematuria.",
    "Musculoskeletal: Reports occasional joint stiffness; denies acute injury.",
    "Neurological: Denies headache, dizziness, or focal weakness.",
    "Psychiatric: Denies depression, anxiety, or suicidal ideation.",
    "Endocrine: Denies polyuria, polydipsia, or heat/cold intolerance.",
    "Hematologic/Lymphatic: Denies easy bruising or lymphadenopathy.",
    "Allergic/Immunologic: NKDA."
  ],
  "physical_exam": [
    "General: Alert, oriented x3, in no acute distress.",
    "Vitals: BP {bp_sys}/{bp_dia}, HR {hr}, RR {rr}, Temp {temp} F, SpO2 {spo2}%.",
    "HEENT: Normocephalic, atraumatic. PERRL. Oropharynx clear.",
    "Neck: Supple, no JVD, no thyromegaly, no lymphadenopathy.",
    "Cardiovascular: RRR, no murmurs/rubs/gallops.",
    "Respiratory: Clear to auscultation bilaterally, no wheezes or rales.",
    "Abdomen: Soft, non-tender, non-distended, normoactive bowel sounds.",
    "Extremities: No clubbing, cyanosis, or edema. Pulses 2+ throughout.",
    "Skin: Warm, dry, intact. No rashes or lesions.",
    "Neurological: CN II-XII grossly intact, strength 5/5 throughout, sensation intact."
  ],
  "assessment_phrases": [
    "Stable on current regimen.",
    "Symptoms suggestive of {condition}; further workup indicated.",
    "Continue current management; reassess in {followup_weeks} weeks.",
    "Will initiate {medication} for symptomatic relief.",
    "Refer to {specialty} for further evaluation.",
    "Patient counseled on lifestyle modifications including diet and exercise."
  ],
  "medications": [
    "Metformin 1000 mg PO BID",
    "Lisinopril 20 mg PO daily",
    "Atorvastatin 40 mg PO QHS",
    "Amlodipine 5 mg PO daily",
    "Levothyroxine 75 mcg PO daily",
    "Albuterol inhaler 90 mcg 2 puffs Q4H PRN",
    "Aspirin 81 mg PO daily",
    "Omeprazole 20 mg PO daily",
    "Sertraline 50 mg PO daily",
    "Hydrochlorothiazide 25 mg PO daily",
    "Gabapentin 300 mg PO TID",
    "Insulin glargine 20 units SC QHS"
  ],
  "specialties": ["cardiology", "endocrinology", "pulmonology", "gastroenterology", "orthopedics", "neurology", "nephrology", "rheumatology"],
  "facilities": [
    "Riverside Medical Center",
    "Lakeshore Family Practice",
    "Northgate Internal Medicine",
    "Summit Cardiology Associates",
    "Heritage Community Hospital",
    "Greenfield Primary Care",
    "Pinewood Specialty Clinic",
    "Crestview Health Partners"
  ],
  "insurance_payers": [
    "Aetna PPO",
    "Blue Cross Blue Shield",
    "Cigna HealthCare",
    "UnitedHealthcare",
    "Humana Medicare Advantage",
    "Medicare Part B",
    "Medicaid",
    "Tricare"
  ]
}
